ctrbuild/__init__.py
ctrbuild/cli.py
ctrbuild-0.1.1.dist-info/METADATA
ctrbuild-0.1.1.dist-info/WHEEL
ctrbuild-0.1.1.dist-info/entry_points.txt
ctrbuild-0.1.1.dist-info/top_level.txt
ctrbuild-0.1.1.dist-info/RECORD
